atomion/__init__.py
atomion/couples.py
atomion/elements.py
atomion/exception.py
atomion/irregularites.py
atomion/raccourcis.py
atomion/objets/__init__.py
atomion/objets/atome.py
atomion/objets/electron.py
atomion/objets/ion.py
atomion/objets/liaison.py
atomion/objets/molecule.py
atomion/objets/neutron.py
atomion/objets/noyau.py
atomion/objets/proton.py
atomion/objets/quark.py
atomion/utile/__init__.py
atomion/utile/acido_basique.py
atomion/utile/equation.py
atomion/utile/oxydo_reduction.py
atomion/utile/typing.py
atomion/utile/utile.py
atomion-1.6.0.dist-info/METADATA
atomion-1.6.0.dist-info/WHEEL
atomion-1.6.0.dist-info/top_level.txt
atomion-1.6.0.dist-info/RECORD
