Metadata-Version: 2.1
Name: atomion
Version: 1.6.0
Summary: Manipuler des concepts physiques/chimiques (atomes, ions, équations, ...) facilement.
Home-page: https://github.com/4surix/atomion
Author: Asurix
Author-email: asurix@outlook.fr
Keywords: quark atome ion molecule equation reaction oxydoreduction fusion
Classifier: Intended Audience :: Education
Classifier: Intended Audience :: Developers
Classifier: Intended Audience :: End Users/Desktop
Classifier: Programming Language :: Python :: 3 :: Only
Classifier: Typing :: Typed
Classifier: Natural Language :: French
Classifier: Programming Language :: Python :: Implementation :: MicroPython
Requires-Python: >=3, <4
